kovacszsolt_add/__init__.py
kovacszsolt_add-0.1.0.dist-info/METADATA
kovacszsolt_add-0.1.0.dist-info/WHEEL
kovacszsolt_add-0.1.0.dist-info/top_level.txt
kovacszsolt_add-0.1.0.dist-info/RECORD
