Metadata-Version: 2.4
Name: kovacszsolt_add
Version: 0.1.0
Summary: Egy egyszerű csomag, amely összead két számot.
Author-email: Zsolt Kovács <te@peldaemail.hu>
License: MIT
Requires-Python: >=3.7
